<?xml version = '1.0' encoding = 'UTF-8'?>
<Diagram class="oracle.dbtools.crest.swingui.logical.DPVLogical" name="Logical" id="439E86F6-595C-178E-70C5-9D6907C4719B">
<createdBy>alex</createdBy>
<modifiedBy>alex</modifiedBy>
<createdTime>2022-09-10 18:38:44 UTC</createdTime>
<autoRoute>false</autoRoute>
<boxInbox>true</boxInbox>
<showLegend>false</showLegend>
<showLabels>true</showLabels>
<showRelAttributes>false</showRelAttributes>
<gridEnabled>false</gridEnabled>
<showGrid>false</showGrid>
<diagramColor>-1</diagramColor>
<display>false</display>
<notation>1</notation>
<objectViews>
<OView class="oracle.dbtools.crest.swingui.logical.TVEntity" oid="6EA9E3CE-A760-41A3-A1F7-93EDC67B0976" otype="Entity" vid="B0A22CC3-E8F7-56E6-8B0D-19E93B13FB61">
<hideElementsInCurrentOnly>false</hideElementsInCurrentOnly>
<bounds x="684" y="194" width="208" height="187"/>
</OView>
<OView class="oracle.dbtools.crest.swingui.logical.TVEntity" oid="9F4E5BA6-711E-B4BA-2D79-54C59405F7E7" otype="Entity" vid="7FD3AAEF-7161-C6F5-5822-E41CB6150520">
<hideElementsInCurrentOnly>false</hideElementsInCurrentOnly>
<bounds x="189" y="196" width="219" height="177"/>
</OView>
</objectViews>
<connectors>
<Connector class="oracle.dbtools.crest.swingui.logical.TVRelation" oid="B8FCA63B-8C8F-693C-2491-882631D27FDB" otype="Relation" vid_source="B0A22CC3-E8F7-56E6-8B0D-19E93B13FB61" vid_target="7FD3AAEF-7161-C6F5-5822-E41CB6150520">
<hideElementsInCurrentOnly>false</hideElementsInCurrentOnly>
<lineWidth>1</lineWidth>
<sourceLabel class="oracle.dbtools.crest.model.design.Label">
<site>0</site>
<labelBounds x="615" y="287" width="40" height="20"/>
<fonts itemClass="oracle.dbtools.crest.model.design.FontObjectWr">
<FontObject>
<foType>Text</foType>
<colorRGB>-16777216</colorRGB>
</FontObject>
</fonts>
</sourceLabel>
<targetLabel class="oracle.dbtools.crest.model.design.Label">
<site>2</site>
<labelBounds x="465" y="287" width="53" height="20"/>
<fonts itemClass="oracle.dbtools.crest.model.design.FontObjectWr">
<FontObject>
<foType>Text</foType>
<colorRGB>-16777216</colorRGB>
</FontObject>
</fonts>
</targetLabel>
<points>
<point x="684" y="284"/>
<point x="408" y="284"/>
</points>
</Connector>
</connectors>
</Diagram>